{
  "seller": [
    {
      "name": "Namrata",
      "password": "Namrata",
      "email": "namrata",
      "id": 1
    },
    {
      "name": "Harshavardhan",
      "password": "Harshavardhan",
      "email": "Harshavardhan",
      "id": 2
    },
    {
      "name": "1",
      "password": "1",
      "email": "1",
      "id": 3
    },
    {
      "name": "1",
      "password": "1",
      "email": "11",
      "id": 4
    }
  ],
  "seller-auth": [
    {
      "name": "1",
      "password": "1",
      "email": "1",
      "id": 0
    },
    {
      "name": "Harshavardhan",
      "password": "12345",
      "email": "h@gmail.com",
      "id": 1
    }
  ],
  "products": [
    {
      "name": "APPLE",
      "price": "40000",
      "color": "Black",
      "category": "SMARTPHONES",
      "description": "An Apple Item",
      "image": "",
      "id": 0
    },
    {
      "name": "SAMSUNG",
      "price": "40000",
      "color": "White",
      "category": "SMARTPHONES",
      "image": "../assets/images/",
      "description": "Samsung Item",
      "id": 1
    },
    {
      "name": "Dell ",
      "price": "55000",
      "color": "Silver",
      "category": "LAPTOPS",
      "image": "../assets/images/",
      "description": "Dell Item",
      "id": 2
    },
    {
      "name": "Boat ",
      "price": "1499",
      "color": "Silver",
      "category": "EARBUDS",
      "image": "../assets/images/",
      "description": "Boat Headset Item",
      "id": 3
    },
    {
      "name": "Oppo",
      "price": 15000,
      "color": "Golden",
      "category": "SMARTPHONES",
      "description": "An Oppo Product",
      "image": "../assets/images/",
      "id": 4
    },
    {
      "name": "",
      "price": "",
      "color": "",
      "category": "",
      "description": "",
      "image": "",
      "id": 5
    }
  ]
}